{"Records":[{"eventVersion":"1.08","userIdentity":{"type":"AWSService","invokedBy":"cloudtrail.amazonaws.com"},"eventTime":"2022-07-18T02:55:06Z","eventSource":"s3.amazonaws.com","eventName":"GetBucketAcl","awsRegion":"us-east-1","sourceIPAddress":"cloudtrail.amazonaws.com","userAgent":"cloudtrail.amazonaws.com","requestParameters":{"bucketName":"aws-cloudtrail-logs-418391250876-e70b6f45","Host":"aws-cloudtrail-logs-418391250876-e70b6f45.s3.us-east-1.amazonaws.com","acl":""},"responseElements":null,"additionalEventData":{"SignatureVersion":"SigV4","CipherSuite":"ECDHE-RSA-AES128-GCM-SHA256","bytesTransferredIn":0,"AuthenticationMethod":"AuthHeader","x-amz-id-2":"8/+3WSCktK07QVy5o48eE0zTQBR/UnHFKJLnq/njMm0vm8nPQYNm15FCoipCvoDlQxqytK7mkpg=","bytesTransferredOut":584},"requestID":"PDJ7HAJSPWJJA07C","eventID":"a71668a1-650d-4659-a143-affebf4af407","readOnly":true,"resources":[{"accountId":"418391250876","type":"AWS::S3::Bucket","ARN":"arn:aws:s3:::aws-cloudtrail-logs-418391250876-e70b6f45"}],"eventType":"AwsApiCall","managementEvent":true,"recipientAccountId":"418391250876","sharedEventID":"f72e5d36-7255-421b-9e3d-35a0b0cc6168","eventCategory":"Management"},{"eventVersion":"1.08","userIdentity":{"type":"AWSService","invokedBy":"cloudtrail.amazonaws.com"},"eventTime":"2022-07-18T02:55:06Z","eventSource":"kms.amazonaws.com","eventName":"GenerateDataKey","awsRegion":"us-east-1","sourceIPAddress":"cloudtrail.amazonaws.com","userAgent":"cloudtrail.amazonaws.com","requestParameters":{"keyId":"arn:aws:kms:us-east-1:418391250876:key/73a0e8df-7933-4d0a-94c2-f2472ed1e32b","encryptionContext":{"aws:cloudtrail:arn":"arn:aws:cloudtrail:us-east-1:418391250876:trail/MainCloudTrail","aws:s3:arn":"arn:aws:s3:::aws-cloudtrail-logs-418391250876-e70b6f45/AWSLogs/418391250876/CloudTrail/us-east-1/2022/07/18/418391250876_CloudTrail_us-east-1_20220718T0250Z_aE6ZkYzwctLA0Fyq.json.gz"},"keySpec":"AES_256"},"responseElements":null,"requestID":"e107993f-5466-4205-a03e-45da7e4e705d","eventID":"a06378c4-b069-40ef-824d-42d29b621079","readOnly":true,"resources":[{"accountId":"418391250876","type":"AWS::KMS::Key","ARN":"arn:aws:kms:us-east-1:418391250876:key/73a0e8df-7933-4d0a-94c2-f2472ed1e32b"}],"eventType":"AwsApiCall","managementEvent":true,"recipientAccountId":"418391250876","sharedEventID":"72a9ad0a-3b82-4b83-ae80-32dd9188d9d9","eventCategory":"Management"},{"eventVersion":"1.08","userIdentity":{"type":"AWSService","invokedBy":"cloudtrail.amazonaws.com"},"eventTime":"2022-07-18T02:55:09Z","eventSource":"s3.amazonaws.com","eventName":"GetBucketAcl","awsRegion":"us-east-1","sourceIPAddress":"cloudtrail.amazonaws.com","userAgent":"cloudtrail.amazonaws.com","requestParameters":{"bucketName":"aws-cloudtrail-logs-418391250876-e70b6f45","Host":"aws-cloudtrail-logs-418391250876-e70b6f45.s3.us-east-1.amazonaws.com","acl":""},"responseElements":null,"additionalEventData":{"SignatureVersion":"SigV4","CipherSuite":"ECDHE-RSA-AES128-GCM-SHA256","bytesTransferredIn":0,"AuthenticationMethod":"AuthHeader","x-amz-id-2":"KZL6BjFP+hNe77ixPyO+4wDGfi9v72exKuSUAmOQjkuxRcCQGgEad+emLhIGkzAGSsLB3WtWBq8=","bytesTransferredOut":584},"requestID":"SMT0EM8CFWGHTVQ1","eventID":"750f1bf0-0cc0-4b47-94b0-365dcf6cd353","readOnly":true,"resources":[{"accountId":"418391250876","type":"AWS::S3::Bucket","ARN":"arn:aws:s3:::aws-cloudtrail-logs-418391250876-e70b6f45"}],"eventType":"AwsApiCall","managementEvent":true,"recipientAccountId":"418391250876","sharedEventID":"2ef5fc0e-db88-4128-b1c6-3d88b3bb75fc","eventCategory":"Management"},{"eventVersion":"1.08","userIdentity":{"type":"AWSService","invokedBy":"cloudtrail.amazonaws.com"},"eventTime":"2022-07-18T02:55:09Z","eventSource":"kms.amazonaws.com","eventName":"GenerateDataKey","awsRegion":"us-east-1","sourceIPAddress":"cloudtrail.amazonaws.com","userAgent":"cloudtrail.amazonaws.com","requestParameters":{"keySpec":"AES_256","encryptionContext":{"aws:cloudtrail:arn":"arn:aws:cloudtrail:us-east-1:418391250876:trail/MainCloudTrail","aws:s3:arn":"arn:aws:s3:::aws-cloudtrail-logs-418391250876-e70b6f45/AWSLogs/418391250876/CloudTrail/us-east-1/2022/07/18/418391250876_CloudTrail_us-east-1_20220718T0250Z_HS51cesenXgWf8rK.json.gz"},"keyId":"arn:aws:kms:us-east-1:418391250876:key/73a0e8df-7933-4d0a-94c2-f2472ed1e32b"},"responseElements":null,"requestID":"4d65a9e2-07fe-4b8f-8266-363e5e078671","eventID":"c736fc95-48b0-4360-98d2-2261c9bf2660","readOnly":true,"resources":[{"accountId":"418391250876","type":"AWS::KMS::Key","ARN":"arn:aws:kms:us-east-1:418391250876:key/73a0e8df-7933-4d0a-94c2-f2472ed1e32b"}],"eventType":"AwsApiCall","managementEvent":true,"recipientAccountId":"418391250876","sharedEventID":"2b0cef67-56c0-428c-b7ff-45b287d6197e","eventCategory":"Management"}]}