{"Records":[{"eventVersion":"1.08","userIdentity":{"type":"AWSService","invokedBy":"cloudtrail.amazonaws.com"},"eventTime":"2022-07-18T14:02:51Z","eventSource":"kms.amazonaws.com","eventName":"GenerateDataKey","awsRegion":"us-east-1","sourceIPAddress":"cloudtrail.amazonaws.com","userAgent":"cloudtrail.amazonaws.com","requestParameters":{"keySpec":"AES_256","encryptionContext":{"aws:cloudtrail:arn":"arn:aws:cloudtrail:us-east-1:418391250876:trail/MainCloudTrail","aws:s3:arn":"arn:aws:s3:::aws-cloudtrail-logs-418391250876-e70b6f45/AWSLogs/418391250876/CloudTrail/us-east-1/2022/07/18/418391250876_CloudTrail_us-east-1_20220718T1400Z_humeUQksNoZwGSVS.json.gz"},"keyId":"arn:aws:kms:us-east-1:418391250876:key/73a0e8df-7933-4d0a-94c2-f2472ed1e32b"},"responseElements":null,"requestID":"1bf7ce1b-1e79-40aa-adf2-575849d0f87e","eventID":"4746f543-7aa6-40db-8153-ad4f32441edc","readOnly":true,"resources":[{"accountId":"418391250876","type":"AWS::KMS::Key","ARN":"arn:aws:kms:us-east-1:418391250876:key/73a0e8df-7933-4d0a-94c2-f2472ed1e32b"}],"eventType":"AwsApiCall","managementEvent":true,"recipientAccountId":"418391250876","sharedEventID":"a036013e-7807-43fd-994e-08776d2b4b72","eventCategory":"Management"},{"eventVersion":"1.08","userIdentity":{"type":"AWSService","invokedBy":"cloudtrail.amazonaws.com"},"eventTime":"2022-07-18T14:02:51Z","eventSource":"s3.amazonaws.com","eventName":"GetBucketAcl","awsRegion":"us-east-1","sourceIPAddress":"cloudtrail.amazonaws.com","userAgent":"cloudtrail.amazonaws.com","requestParameters":{"bucketName":"aws-cloudtrail-logs-418391250876-e70b6f45","Host":"aws-cloudtrail-logs-418391250876-e70b6f45.s3.us-east-1.amazonaws.com","acl":""},"responseElements":null,"additionalEventData":{"SignatureVersion":"SigV4","CipherSuite":"ECDHE-RSA-AES128-GCM-SHA256","bytesTransferredIn":0,"AuthenticationMethod":"AuthHeader","x-amz-id-2":"4ky6XV3LYA1hGiRskcy30Uivyix9gpVWjQynqfAaTYPQ8Q47beUtBjokGv41OOqcfovqGYVB1xJk+kziNPUECA==","bytesTransferredOut":584},"requestID":"F7ZY20A1C2CDEG1T","eventID":"671cca4c-bfe3-4e98-b79e-7b0ffea10263","readOnly":true,"resources":[{"accountId":"418391250876","type":"AWS::S3::Bucket","ARN":"arn:aws:s3:::aws-cloudtrail-logs-418391250876-e70b6f45"}],"eventType":"AwsApiCall","managementEvent":true,"recipientAccountId":"418391250876","sharedEventID":"b4e05d82-c1a9-4ced-8b94-049be4e39a58","eventCategory":"Management"},{"eventVersion":"1.08","userIdentity":{"type":"AWSService","invokedBy":"cloudtrail.amazonaws.com"},"eventTime":"2022-07-18T14:02:49Z","eventSource":"s3.amazonaws.com","eventName":"GetBucketAcl","awsRegion":"us-east-1","sourceIPAddress":"cloudtrail.amazonaws.com","userAgent":"cloudtrail.amazonaws.com","requestParameters":{"bucketName":"aws-cloudtrail-logs-418391250876-e70b6f45","Host":"aws-cloudtrail-logs-418391250876-e70b6f45.s3.us-east-1.amazonaws.com","acl":""},"responseElements":null,"additionalEventData":{"SignatureVersion":"SigV4","CipherSuite":"ECDHE-RSA-AES128-GCM-SHA256","bytesTransferredIn":0,"AuthenticationMethod":"AuthHeader","x-amz-id-2":"omc953sfyXu/dfg6dOhU9PZ+kX8EynJCPp0OIaWY97zHyToOj3SZnxQp0T4J3h5zElALQ4P7x2I=","bytesTransferredOut":584},"requestID":"0315KNHFXC4MFP9P","eventID":"b95d91b6-be78-46db-aa24-e3eb3e402602","readOnly":true,"resources":[{"accountId":"418391250876","type":"AWS::S3::Bucket","ARN":"arn:aws:s3:::aws-cloudtrail-logs-418391250876-e70b6f45"}],"eventType":"AwsApiCall","managementEvent":true,"recipientAccountId":"418391250876","sharedEventID":"07d52fc5-64ea-4f22-a8ca-918407f4bc0d","eventCategory":"Management"},{"eventVersion":"1.08","userIdentity":{"type":"AWSService","invokedBy":"cloudtrail.amazonaws.com"},"eventTime":"2022-07-18T14:02:49Z","eventSource":"kms.amazonaws.com","eventName":"GenerateDataKey","awsRegion":"us-east-1","sourceIPAddress":"cloudtrail.amazonaws.com","userAgent":"cloudtrail.amazonaws.com","requestParameters":{"encryptionContext":{"aws:cloudtrail:arn":"arn:aws:cloudtrail:us-east-1:418391250876:trail/MainCloudTrail","aws:s3:arn":"arn:aws:s3:::aws-cloudtrail-logs-418391250876-e70b6f45/AWSLogs/418391250876/CloudTrail/us-east-1/2022/07/18/418391250876_CloudTrail_us-east-1_20220718T1400Z_2ILMvAZdUFpQKCjr.json.gz"},"keySpec":"AES_256","keyId":"arn:aws:kms:us-east-1:418391250876:key/73a0e8df-7933-4d0a-94c2-f2472ed1e32b"},"responseElements":null,"requestID":"d1ebd632-3c7c-4b18-83e3-a3345f0da35f","eventID":"dd4630e4-54b0-4068-af59-914489e830e0","readOnly":true,"resources":[{"accountId":"418391250876","type":"AWS::KMS::Key","ARN":"arn:aws:kms:us-east-1:418391250876:key/73a0e8df-7933-4d0a-94c2-f2472ed1e32b"}],"eventType":"AwsApiCall","managementEvent":true,"recipientAccountId":"418391250876","sharedEventID":"106a98d2-98db-48ef-a2ca-8132d03448b8","eventCategory":"Management"},{"eventVersion":"1.08","userIdentity":{"type":"AWSService","invokedBy":"cloudtrail.amazonaws.com"},"eventTime":"2022-07-18T14:07:58Z","eventSource":"s3.amazonaws.com","eventName":"GetBucketAcl","awsRegion":"us-east-1","sourceIPAddress":"cloudtrail.amazonaws.com","userAgent":"cloudtrail.amazonaws.com","requestParameters":{"bucketName":"aws-cloudtrail-logs-418391250876-e70b6f45","Host":"aws-cloudtrail-logs-418391250876-e70b6f45.s3.us-east-1.amazonaws.com","acl":""},"responseElements":null,"additionalEventData":{"SignatureVersion":"SigV4","CipherSuite":"ECDHE-RSA-AES128-GCM-SHA256","bytesTransferredIn":0,"AuthenticationMethod":"AuthHeader","x-amz-id-2":"CRw3Cr98i4nTQg8EjH5xYirTlZk1eN59NYfeKBUlEeIJ4JOms7CqFO76RPq2R7jH5KVU5+cDk5o=","bytesTransferredOut":584},"requestID":"1X2H7NAFK9TEHRF4","eventID":"d3eba7ae-4848-4209-8b4e-132eda06ea98","readOnly":true,"resources":[{"accountId":"418391250876","type":"AWS::S3::Bucket","ARN":"arn:aws:s3:::aws-cloudtrail-logs-418391250876-e70b6f45"}],"eventType":"AwsApiCall","managementEvent":true,"recipientAccountId":"418391250876","sharedEventID":"b1f0e549-203e-4b85-b3ca-140581a9ecd9","eventCategory":"Management"},{"eventVersion":"1.08","userIdentity":{"type":"AWSService","invokedBy":"cloudtrail.amazonaws.com"},"eventTime":"2022-07-18T14:07:58Z","eventSource":"kms.amazonaws.com","eventName":"GenerateDataKey","awsRegion":"us-east-1","sourceIPAddress":"cloudtrail.amazonaws.com","userAgent":"cloudtrail.amazonaws.com","requestParameters":{"keySpec":"AES_256","keyId":"arn:aws:kms:us-east-1:418391250876:key/73a0e8df-7933-4d0a-94c2-f2472ed1e32b","encryptionContext":{"aws:cloudtrail:arn":"arn:aws:cloudtrail:us-east-1:418391250876:trail/MainCloudTrail","aws:s3:arn":"arn:aws:s3:::aws-cloudtrail-logs-418391250876-e70b6f45/AWSLogs/418391250876/CloudTrail/us-east-1/2022/07/18/418391250876_CloudTrail_us-east-1_20220718T1410Z_NNDg14xEUpKwy2Oh.json.gz"}},"responseElements":null,"requestID":"a1b4df65-7cf1-41fc-80d2-df5754247881","eventID":"8345b41d-b4fe-4ed7-a8c5-0499f3375dbc","readOnly":true,"resources":[{"accountId":"418391250876","type":"AWS::KMS::Key","ARN":"arn:aws:kms:us-east-1:418391250876:key/73a0e8df-7933-4d0a-94c2-f2472ed1e32b"}],"eventType":"AwsApiCall","managementEvent":true,"recipientAccountId":"418391250876","sharedEventID":"31e15ae1-f917-46a7-81c1-1fa50fdd205c","eventCategory":"Management"},{"eventVersion":"1.08","userIdentity":{"type":"AWSService","invokedBy":"cloudtrail.amazonaws.com"},"eventTime":"2022-07-18T14:08:02Z","eventSource":"kms.amazonaws.com","eventName":"GenerateDataKey","awsRegion":"us-east-1","sourceIPAddress":"cloudtrail.amazonaws.com","userAgent":"cloudtrail.amazonaws.com","requestParameters":{"encryptionContext":{"aws:cloudtrail:arn":"arn:aws:cloudtrail:us-east-1:418391250876:trail/MainCloudTrail","aws:s3:arn":"arn:aws:s3:::aws-cloudtrail-logs-418391250876-e70b6f45/AWSLogs/418391250876/CloudTrail/us-east-1/2022/07/18/418391250876_CloudTrail_us-east-1_20220718T1405Z_Wyr6dguPeLlD3gGH.json.gz"},"keySpec":"AES_256","keyId":"arn:aws:kms:us-east-1:418391250876:key/73a0e8df-7933-4d0a-94c2-f2472ed1e32b"},"responseElements":null,"requestID":"5ca16065-13e2-4bc2-ac1e-ab11c28d77c9","eventID":"046c890e-dd18-464d-b701-24713bbd4d74","readOnly":true,"resources":[{"accountId":"418391250876","type":"AWS::KMS::Key","ARN":"arn:aws:kms:us-east-1:418391250876:key/73a0e8df-7933-4d0a-94c2-f2472ed1e32b"}],"eventType":"AwsApiCall","managementEvent":true,"recipientAccountId":"418391250876","sharedEventID":"c0a170e8-b73f-4a1e-8dd4-15338d8c3709","eventCategory":"Management"},{"eventVersion":"1.08","userIdentity":{"type":"AWSService","invokedBy":"cloudtrail.amazonaws.com"},"eventTime":"2022-07-18T14:08:02Z","eventSource":"s3.amazonaws.com","eventName":"GetBucketAcl","awsRegion":"us-east-1","sourceIPAddress":"cloudtrail.amazonaws.com","userAgent":"cloudtrail.amazonaws.com","requestParameters":{"bucketName":"aws-cloudtrail-logs-418391250876-e70b6f45","Host":"aws-cloudtrail-logs-418391250876-e70b6f45.s3.us-east-1.amazonaws.com","acl":""},"responseElements":null,"additionalEventData":{"SignatureVersion":"SigV4","CipherSuite":"ECDHE-RSA-AES128-GCM-SHA256","bytesTransferredIn":0,"AuthenticationMethod":"AuthHeader","x-amz-id-2":"SffwugDgKperOsp9MLIU+MAor4fyWS2ZcR/Px35ZXwCP+cuSxD3yHH0KiCYnpKZffDLncpmmLT8=","bytesTransferredOut":584},"requestID":"MGX4EY9SAS31PN4H","eventID":"3eedf042-e335-480c-94a2-b9c87d594007","readOnly":true,"resources":[{"accountId":"418391250876","type":"AWS::S3::Bucket","ARN":"arn:aws:s3:::aws-cloudtrail-logs-418391250876-e70b6f45"}],"eventType":"AwsApiCall","managementEvent":true,"recipientAccountId":"418391250876","sharedEventID":"457cd0b5-4961-4411-b8c1-e4fee24dbb5d","eventCategory":"Management"}]}