{"Records":[{"eventVersion":"1.08","userIdentity":{"type":"AWSService","invokedBy":"cloudtrail.amazonaws.com"},"eventTime":"2022-07-18T00:09:38Z","eventSource":"kms.amazonaws.com","eventName":"GenerateDataKey","awsRegion":"us-east-1","sourceIPAddress":"cloudtrail.amazonaws.com","userAgent":"cloudtrail.amazonaws.com","requestParameters":{"keySpec":"AES_256","keyId":"arn:aws:kms:us-east-1:418391250876:key/73a0e8df-7933-4d0a-94c2-f2472ed1e32b","encryptionContext":{"aws:cloudtrail:arn":"arn:aws:cloudtrail:us-east-1:418391250876:trail/MainCloudTrail","aws:s3:arn":"arn:aws:s3:::aws-cloudtrail-logs-418391250876-e70b6f45/AWSLogs/418391250876/CloudTrail/us-east-1/2022/07/18/418391250876_CloudTrail_us-east-1_20220718T0005Z_9In48aPkaSvXv3fP.json.gz"}},"responseElements":null,"requestID":"e342996f-be55-40a1-813c-9c373f5b6c36","eventID":"8298049a-7c1d-454d-87b7-007fef4b50dc","readOnly":true,"resources":[{"accountId":"418391250876","type":"AWS::KMS::Key","ARN":"arn:aws:kms:us-east-1:418391250876:key/73a0e8df-7933-4d0a-94c2-f2472ed1e32b"}],"eventType":"AwsApiCall","managementEvent":true,"recipientAccountId":"418391250876","sharedEventID":"a64c88cb-005f-4839-9768-2030f537f699","eventCategory":"Management"},{"eventVersion":"1.08","userIdentity":{"type":"AWSService","invokedBy":"cloudtrail.amazonaws.com"},"eventTime":"2022-07-18T00:09:43Z","eventSource":"kms.amazonaws.com","eventName":"GenerateDataKey","awsRegion":"us-east-1","sourceIPAddress":"cloudtrail.amazonaws.com","userAgent":"cloudtrail.amazonaws.com","requestParameters":{"keyId":"arn:aws:kms:us-east-1:418391250876:key/73a0e8df-7933-4d0a-94c2-f2472ed1e32b","encryptionContext":{"aws:cloudtrail:arn":"arn:aws:cloudtrail:us-east-1:418391250876:trail/MainCloudTrail","aws:s3:arn":"arn:aws:s3:::aws-cloudtrail-logs-418391250876-e70b6f45/AWSLogs/418391250876/CloudTrail/us-east-1/2022/07/18/418391250876_CloudTrail_us-east-1_20220718T0010Z_trtL595ZLmjtUJvr.json.gz"},"keySpec":"AES_256"},"responseElements":null,"requestID":"f46b2ff3-a058-4134-85b5-80ba09c0ce2e","eventID":"9fc8a5d9-1d1d-4512-983c-ce44efa90eb4","readOnly":true,"resources":[{"accountId":"418391250876","type":"AWS::KMS::Key","ARN":"arn:aws:kms:us-east-1:418391250876:key/73a0e8df-7933-4d0a-94c2-f2472ed1e32b"}],"eventType":"AwsApiCall","managementEvent":true,"recipientAccountId":"418391250876","sharedEventID":"03887033-771c-4cb0-9d3d-a4dd06ea562e","eventCategory":"Management"},{"eventVersion":"1.08","userIdentity":{"type":"AWSService","invokedBy":"cloudtrail.amazonaws.com"},"eventTime":"2022-07-18T00:09:43Z","eventSource":"s3.amazonaws.com","eventName":"GetBucketAcl","awsRegion":"us-east-1","sourceIPAddress":"cloudtrail.amazonaws.com","userAgent":"cloudtrail.amazonaws.com","requestParameters":{"bucketName":"aws-cloudtrail-logs-418391250876-e70b6f45","Host":"aws-cloudtrail-logs-418391250876-e70b6f45.s3.us-east-1.amazonaws.com","acl":""},"responseElements":null,"additionalEventData":{"SignatureVersion":"SigV4","CipherSuite":"ECDHE-RSA-AES128-GCM-SHA256","bytesTransferredIn":0,"AuthenticationMethod":"AuthHeader","x-amz-id-2":"2JQL/McNCmZF13RDBRN6M33/K0w3UuPQRBAwoY0yf4/QA49mMdvHDCPhPa+GEOxRR6zVU0bfE/I=","bytesTransferredOut":584},"requestID":"HP2F3DANEFMZQ9K1","eventID":"e9bdfeff-1361-4f30-a0c5-ac5405535459","readOnly":true,"resources":[{"accountId":"418391250876","type":"AWS::S3::Bucket","ARN":"arn:aws:s3:::aws-cloudtrail-logs-418391250876-e70b6f45"}],"eventType":"AwsApiCall","managementEvent":true,"recipientAccountId":"418391250876","sharedEventID":"98fd8edf-32e3-4c9e-ba52-2ab2a631d2fd","eventCategory":"Management"}]}