{"Records":[{"eventVersion":"1.08","userIdentity":{"type":"AWSService","invokedBy":"cloudtrail.amazonaws.com"},"eventTime":"2022-07-18T13:31:47Z","eventSource":"s3.amazonaws.com","eventName":"GetBucketAcl","awsRegion":"us-east-1","sourceIPAddress":"cloudtrail.amazonaws.com","userAgent":"cloudtrail.amazonaws.com","requestParameters":{"bucketName":"aws-cloudtrail-logs-418391250876-e70b6f45","Host":"aws-cloudtrail-logs-418391250876-e70b6f45.s3.us-east-1.amazonaws.com","acl":""},"responseElements":null,"additionalEventData":{"SignatureVersion":"SigV4","CipherSuite":"ECDHE-RSA-AES128-GCM-SHA256","bytesTransferredIn":0,"AuthenticationMethod":"AuthHeader","x-amz-id-2":"e74wd0j77RBJW/SfmssFySynt5xAZ5Iq6HQIEsMRfll8U2ysorQqT8oGVbBFwzhx8di/OC3ZnHE=","bytesTransferredOut":584},"requestID":"RSD4X8VF3BKJJEP5","eventID":"d736a81e-22f4-477b-9128-8e99a55e5ea1","readOnly":true,"resources":[{"accountId":"418391250876","type":"AWS::S3::Bucket","ARN":"arn:aws:s3:::aws-cloudtrail-logs-418391250876-e70b6f45"}],"eventType":"AwsApiCall","managementEvent":true,"recipientAccountId":"418391250876","sharedEventID":"2d0b0341-90ac-4da9-af1e-bdff4e174f50","eventCategory":"Management"},{"eventVersion":"1.08","userIdentity":{"type":"AWSService","invokedBy":"cloudtrail.amazonaws.com"},"eventTime":"2022-07-18T13:31:47Z","eventSource":"kms.amazonaws.com","eventName":"GenerateDataKey","awsRegion":"us-east-1","sourceIPAddress":"cloudtrail.amazonaws.com","userAgent":"cloudtrail.amazonaws.com","requestParameters":{"encryptionContext":{"aws:cloudtrail:arn":"arn:aws:cloudtrail:us-east-1:418391250876:trail/MainCloudTrail","aws:s3:arn":"arn:aws:s3:::aws-cloudtrail-logs-418391250876-e70b6f45/AWSLogs/418391250876/CloudTrail/us-east-1/2022/07/18/418391250876_CloudTrail_us-east-1_20220718T1330Z_bnQ5S3ao3osU39Fl.json.gz"},"keyId":"arn:aws:kms:us-east-1:418391250876:key/73a0e8df-7933-4d0a-94c2-f2472ed1e32b","keySpec":"AES_256"},"responseElements":null,"requestID":"532cb868-ffe3-46f3-a371-af8cb031ecdd","eventID":"8190cf45-56b7-49e5-a843-f88243b996f4","readOnly":true,"resources":[{"accountId":"418391250876","type":"AWS::KMS::Key","ARN":"arn:aws:kms:us-east-1:418391250876:key/73a0e8df-7933-4d0a-94c2-f2472ed1e32b"}],"eventType":"AwsApiCall","managementEvent":true,"recipientAccountId":"418391250876","sharedEventID":"c3e14905-05e8-479f-9e7a-a6a54684db9e","eventCategory":"Management"},{"eventVersion":"1.08","userIdentity":{"type":"AWSService","invokedBy":"cloudtrail.amazonaws.com"},"eventTime":"2022-07-18T13:31:50Z","eventSource":"kms.amazonaws.com","eventName":"GenerateDataKey","awsRegion":"us-east-1","sourceIPAddress":"cloudtrail.amazonaws.com","userAgent":"cloudtrail.amazonaws.com","requestParameters":{"keyId":"arn:aws:kms:us-east-1:418391250876:key/73a0e8df-7933-4d0a-94c2-f2472ed1e32b","keySpec":"AES_256","encryptionContext":{"aws:cloudtrail:arn":"arn:aws:cloudtrail:us-east-1:418391250876:trail/MainCloudTrail","aws:s3:arn":"arn:aws:s3:::aws-cloudtrail-logs-418391250876-e70b6f45/AWSLogs/418391250876/CloudTrail/us-east-1/2022/07/18/418391250876_CloudTrail_us-east-1_20220718T1330Z_Z7pvPhsimmWDF7aP.json.gz"}},"responseElements":null,"requestID":"afd64a18-d5fc-4203-98d8-f930f6581c5d","eventID":"0c2c62f3-86a8-40ab-a4fe-cc482b15cb4e","readOnly":true,"resources":[{"accountId":"418391250876","type":"AWS::KMS::Key","ARN":"arn:aws:kms:us-east-1:418391250876:key/73a0e8df-7933-4d0a-94c2-f2472ed1e32b"}],"eventType":"AwsApiCall","managementEvent":true,"recipientAccountId":"418391250876","sharedEventID":"42a9659d-db6c-4a3c-a0ec-601d68a53c4d","eventCategory":"Management"},{"eventVersion":"1.08","userIdentity":{"type":"AWSService","invokedBy":"cloudtrail.amazonaws.com"},"eventTime":"2022-07-18T13:31:50Z","eventSource":"s3.amazonaws.com","eventName":"GetBucketAcl","awsRegion":"us-east-1","sourceIPAddress":"cloudtrail.amazonaws.com","userAgent":"cloudtrail.amazonaws.com","requestParameters":{"bucketName":"aws-cloudtrail-logs-418391250876-e70b6f45","Host":"aws-cloudtrail-logs-418391250876-e70b6f45.s3.us-east-1.amazonaws.com","acl":""},"responseElements":null,"additionalEventData":{"SignatureVersion":"SigV4","CipherSuite":"ECDHE-RSA-AES128-GCM-SHA256","bytesTransferredIn":0,"AuthenticationMethod":"AuthHeader","x-amz-id-2":"5fYgrjBh5z+5MrOmeRLu49ojFmL4k+D94RNiUu0HjmL5XetX4RUEB4zsS0HCE9ow4B+ou03tMV0=","bytesTransferredOut":584},"requestID":"GK8TKSE76X2S0H3N","eventID":"a0d79995-a145-4388-b1fc-d7730412b746","readOnly":true,"resources":[{"accountId":"418391250876","type":"AWS::S3::Bucket","ARN":"arn:aws:s3:::aws-cloudtrail-logs-418391250876-e70b6f45"}],"eventType":"AwsApiCall","managementEvent":true,"recipientAccountId":"418391250876","sharedEventID":"d99297f1-2818-4796-a2af-4ece7430e30c","eventCategory":"Management"}]}