{"Records":[{"eventVersion":"1.08","userIdentity":{"type":"AWSService","invokedBy":"cloudtrail.amazonaws.com"},"eventTime":"2022-07-18T22:50:29Z","eventSource":"kms.amazonaws.com","eventName":"GenerateDataKey","awsRegion":"us-east-1","sourceIPAddress":"cloudtrail.amazonaws.com","userAgent":"cloudtrail.amazonaws.com","requestParameters":{"keyId":"arn:aws:kms:us-east-1:418391250876:key/73a0e8df-7933-4d0a-94c2-f2472ed1e32b","keySpec":"AES_256","encryptionContext":{"aws:cloudtrail:arn":"arn:aws:cloudtrail:us-east-1:418391250876:trail/MainCloudTrail","aws:s3:arn":"arn:aws:s3:::aws-cloudtrail-logs-418391250876-e70b6f45/AWSLogs/418391250876/CloudTrail/us-east-1/2022/07/18/418391250876_CloudTrail_us-east-1_20220718T2255Z_qunIPpeX45dSb13u.json.gz"}},"responseElements":null,"requestID":"a577a400-7ad8-45f9-8fcc-eb558cc858f4","eventID":"8b120c94-4d50-4c69-b943-84bb56be5655","readOnly":true,"resources":[{"accountId":"418391250876","type":"AWS::KMS::Key","ARN":"arn:aws:kms:us-east-1:418391250876:key/73a0e8df-7933-4d0a-94c2-f2472ed1e32b"}],"eventType":"AwsApiCall","managementEvent":true,"recipientAccountId":"418391250876","sharedEventID":"4554bd26-ddc9-4f1a-8aa9-b9e5400c10e2","eventCategory":"Management"},{"eventVersion":"1.08","userIdentity":{"type":"AWSService","invokedBy":"cloudtrail.amazonaws.com"},"eventTime":"2022-07-18T22:50:29Z","eventSource":"s3.amazonaws.com","eventName":"GetBucketAcl","awsRegion":"us-east-1","sourceIPAddress":"cloudtrail.amazonaws.com","userAgent":"cloudtrail.amazonaws.com","requestParameters":{"bucketName":"aws-cloudtrail-logs-418391250876-e70b6f45","Host":"aws-cloudtrail-logs-418391250876-e70b6f45.s3.us-east-1.amazonaws.com","acl":""},"responseElements":null,"additionalEventData":{"SignatureVersion":"SigV4","CipherSuite":"ECDHE-RSA-AES128-GCM-SHA256","bytesTransferredIn":0,"AuthenticationMethod":"AuthHeader","x-amz-id-2":"uAjyAQmgMoQOQcjlYk96EtlTURGZbELUmDckVwnSwBdKXX4v4w3Ow2WsrLh1cpZxGk7FZQfWMpM=","bytesTransferredOut":584},"requestID":"1WS7CDXDMQMQ03NG","eventID":"0b1046dc-be9a-48d0-be8b-dc3952ed967c","readOnly":true,"resources":[{"accountId":"418391250876","type":"AWS::S3::Bucket","ARN":"arn:aws:s3:::aws-cloudtrail-logs-418391250876-e70b6f45"}],"eventType":"AwsApiCall","managementEvent":true,"recipientAccountId":"418391250876","sharedEventID":"ba126889-39f0-44d0-8295-ca93a605e7b6","eventCategory":"Management"},{"eventVersion":"1.08","userIdentity":{"type":"AWSService","invokedBy":"cloudtrail.amazonaws.com"},"eventTime":"2022-07-18T22:55:18Z","eventSource":"s3.amazonaws.com","eventName":"GetBucketAcl","awsRegion":"us-east-1","sourceIPAddress":"cloudtrail.amazonaws.com","userAgent":"cloudtrail.amazonaws.com","requestParameters":{"bucketName":"aws-cloudtrail-logs-418391250876-e70b6f45","Host":"aws-cloudtrail-logs-418391250876-e70b6f45.s3.us-east-1.amazonaws.com","acl":""},"responseElements":null,"additionalEventData":{"SignatureVersion":"SigV4","CipherSuite":"ECDHE-RSA-AES128-GCM-SHA256","bytesTransferredIn":0,"AuthenticationMethod":"AuthHeader","x-amz-id-2":"mmjwqUhi07C1px6LXieMP+KYmL7lVz3iQKD1gctDY7p5tsTcM993MjunWDE/a/dxn31wK22m8jU=","bytesTransferredOut":584},"requestID":"M2XDYEV1TT6MDAHV","eventID":"1f7adcdc-0c53-4b9f-8515-b8ebf98e8d4e","readOnly":true,"resources":[{"accountId":"418391250876","type":"AWS::S3::Bucket","ARN":"arn:aws:s3:::aws-cloudtrail-logs-418391250876-e70b6f45"}],"eventType":"AwsApiCall","managementEvent":true,"recipientAccountId":"418391250876","sharedEventID":"f21278cd-5b13-43d0-8199-343ace13824c","eventCategory":"Management"},{"eventVersion":"1.08","userIdentity":{"type":"AWSService","invokedBy":"cloudtrail.amazonaws.com"},"eventTime":"2022-07-18T22:55:18Z","eventSource":"kms.amazonaws.com","eventName":"GenerateDataKey","awsRegion":"us-east-1","sourceIPAddress":"cloudtrail.amazonaws.com","userAgent":"cloudtrail.amazonaws.com","requestParameters":{"encryptionContext":{"aws:cloudtrail:arn":"arn:aws:cloudtrail:us-east-1:418391250876:trail/MainCloudTrail","aws:s3:arn":"arn:aws:s3:::aws-cloudtrail-logs-418391250876-e70b6f45/AWSLogs/418391250876/CloudTrail/us-east-1/2022/07/18/418391250876_CloudTrail_us-east-1_20220718T2255Z_ViwwabV6EdkbYIb6.json.gz"},"keySpec":"AES_256","keyId":"arn:aws:kms:us-east-1:418391250876:key/73a0e8df-7933-4d0a-94c2-f2472ed1e32b"},"responseElements":null,"requestID":"d37d8189-05f6-4b5c-a402-15a5dae92f36","eventID":"ef2debff-2824-488d-b453-3069b3b19a45","readOnly":true,"resources":[{"accountId":"418391250876","type":"AWS::KMS::Key","ARN":"arn:aws:kms:us-east-1:418391250876:key/73a0e8df-7933-4d0a-94c2-f2472ed1e32b"}],"eventType":"AwsApiCall","managementEvent":true,"recipientAccountId":"418391250876","sharedEventID":"7e535298-cad1-46a3-a539-de7da12d18af","eventCategory":"Management"},{"eventVersion":"1.08","userIdentity":{"type":"AWSService","invokedBy":"cloudtrail.amazonaws.com"},"eventTime":"2022-07-18T22:55:32Z","eventSource":"kms.amazonaws.com","eventName":"GenerateDataKey","awsRegion":"us-east-1","sourceIPAddress":"cloudtrail.amazonaws.com","userAgent":"cloudtrail.amazonaws.com","requestParameters":{"keySpec":"AES_256","keyId":"arn:aws:kms:us-east-1:418391250876:key/73a0e8df-7933-4d0a-94c2-f2472ed1e32b","encryptionContext":{"aws:cloudtrail:arn":"arn:aws:cloudtrail:us-east-1:418391250876:trail/MainCloudTrail","aws:s3:arn":"arn:aws:s3:::aws-cloudtrail-logs-418391250876-e70b6f45/AWSLogs/418391250876/CloudTrail/us-east-1/2022/07/18/418391250876_CloudTrail_us-east-1_20220718T2255Z_Ge4LRqoeBAGPvbJd.json.gz"}},"responseElements":null,"requestID":"124de28c-a88b-45a5-8a77-12e73b4b6b44","eventID":"02633c1c-d503-4468-96d3-54238a16d34c","readOnly":true,"resources":[{"accountId":"418391250876","type":"AWS::KMS::Key","ARN":"arn:aws:kms:us-east-1:418391250876:key/73a0e8df-7933-4d0a-94c2-f2472ed1e32b"}],"eventType":"AwsApiCall","managementEvent":true,"recipientAccountId":"418391250876","sharedEventID":"cac2e6ef-5827-4e2a-81c1-f9edb68d7ddf","eventCategory":"Management"},{"eventVersion":"1.08","userIdentity":{"type":"AWSService","invokedBy":"cloudtrail.amazonaws.com"},"eventTime":"2022-07-18T22:55:32Z","eventSource":"s3.amazonaws.com","eventName":"GetBucketAcl","awsRegion":"us-east-1","sourceIPAddress":"cloudtrail.amazonaws.com","userAgent":"cloudtrail.amazonaws.com","requestParameters":{"bucketName":"aws-cloudtrail-logs-418391250876-e70b6f45","Host":"aws-cloudtrail-logs-418391250876-e70b6f45.s3.us-east-1.amazonaws.com","acl":""},"responseElements":null,"additionalEventData":{"SignatureVersion":"SigV4","CipherSuite":"ECDHE-RSA-AES128-GCM-SHA256","bytesTransferredIn":0,"AuthenticationMethod":"AuthHeader","x-amz-id-2":"UwrygFlY00YAeUS2du/7/IDPL8jdylbRjqnQHnXaeSPfq1EMveahLNU7reiEr+rOvnt+fQg4qXw=","bytesTransferredOut":584},"requestID":"E8HJE63EPJ9XCQ4B","eventID":"f06ceb9c-80cf-443a-b3ed-3c8a3d5a3158","readOnly":true,"resources":[{"accountId":"418391250876","type":"AWS::S3::Bucket","ARN":"arn:aws:s3:::aws-cloudtrail-logs-418391250876-e70b6f45"}],"eventType":"AwsApiCall","managementEvent":true,"recipientAccountId":"418391250876","sharedEventID":"cbad33cb-01a6-40ba-a8bc-10d5831e3245","eventCategory":"Management"}]}